django_generic_hybrid_views
