Metadata-Version: 1.1
Name: django-generic-hybrid-class-based-views
Version: 0.4.0
Summary: Generic Hybrid class based views for the webframework Django.
Home-page: https://github.com/T1mbo96/django_generic_hybrid_views/archive/refs/tags/v_040.tar.gz
Author: Timo Michel
Author-email: TimoM96@outlook.de
License: MIT
Keywords: django,json,hybrid
Platform: UNKNOWN
Classifier: Development Status :: 3 - Alpha
Classifier: Intended Audience :: Developers
Classifier: Topic :: Software Development :: Build Tools
Classifier: License :: OSI Approved :: MIT License
Classifier: Programming Language :: Python :: 3
